at_client/__init__.py
at_client/atclient.py
at_client/common/__init__.py
at_client/common/atsign.py
at_client/common/keys.py
at_client/common/metadata.py
at_client/connections/__init__.py
at_client/connections/address.py
at_client/connections/atconnection.py
at_client/connections/atmonitorconnection.py
at_client/connections/atrootconnection.py
at_client/connections/atsecondaryconnection.py
at_client/connections/notification/atevents.py
at_client/connections/notification/atnotification.py
at_client/connections/response.py
at_client/exception/__init__.py
at_client/exception/atexception.py
at_client/util/__init__.py
at_client/util/atconstants.py
at_client/util/authutil.py
at_client/util/encryptionutil.py
at_client/util/keystringutil.py
at_client/util/keysutil.py
at_client/util/onboardingutil.py
at_client/util/registerutil.py
at_client/util/socketutil.py
at_client/util/syncdecorator.py
at_client/util/timeutil.py
at_client/util/verbbuilder.py
atsdk-0.2.52.dist-info/LICENSE
atsdk-0.2.52.dist-info/METADATA
atsdk-0.2.52.dist-info/WHEEL
atsdk-0.2.52.dist-info/RECORD
