Metadata-Version: 2.3
Name: atsdk
Version: 0.2.52
Summary: Python SDK for atPlatform
License: BSD-3-Clause
Author: Umang Shah
Author-email: shahumang19@gmail.com
Maintainer: Chris Swan
Maintainer-email: chris@atsign.com
Requires-Python: >=3.9.2
Classifier: License :: OSI Approved :: BSD License
Classifier: Programming Language :: Python :: 3
Classifier: Programming Language :: Python :: 3.10
Classifier: Programming Language :: Python :: 3.11
Classifier: Programming Language :: Python :: 3.12
Classifier: Programming Language :: Python :: 3.13
Requires-Dist: cryptography (==46.0.3)
Requires-Dist: python-dateutil (==2.9.0.post0)
Requires-Dist: requests (==2.32.5)
Project-URL: Homepage, https://github.com/atsign-foundation/at_python
